celer/PN_logreg.cp310-win_amd64.pyd
celer/PN_logreg.pyx
celer/__init__.py
celer/cython_utils.cp310-win_amd64.pyd
celer/cython_utils.pxd
celer/cython_utils.pyx
celer/dropin_sklearn.py
celer/group_fast.cp310-win_amd64.pyd
celer/group_fast.pyx
celer/homotopy.py
celer/lasso_fast.cp310-win_amd64.pyd
celer/lasso_fast.pyx
celer/multitask_fast.cp310-win_amd64.pyd
celer/multitask_fast.pyx
celer/plot_utils.py
celer/datasets/__init__.py
celer/datasets/climate.py
celer/datasets/libsvm.py
celer/datasets/ml_uci.py
celer/datasets/simulated.py
celer/datasets/tests/test_datasets.py
celer/tests/test_docstring_parameters.py
celer/tests/test_enet.py
celer/tests/test_lasso.py
celer/tests/test_logreg.py
celer/tests/test_mtl.py
celer/utils/__init__.py
celer/utils/testing.py
celer-0.7.4.dist-info/licenses/LICENSE
celer-0.7.4.dist-info/METADATA
celer-0.7.4.dist-info/WHEEL
celer-0.7.4.dist-info/top_level.txt
celer-0.7.4.dist-info/RECORD
