Metadata-Version: 2.4
Name: celer
Version: 0.7.4
Summary: A fast algorithm with dual extrapolation for sparse problems
Author-email: Mathurin Massias <mathurin.massias@gmail.com>
License: BSD (3-clause)
Project-URL: documentation, https://mathurinm.github.io/celer/
Project-URL: repository, https://github.com/mathurinm/celer.git
License-File: LICENSE
Requires-Dist: seaborn>=0.7
Requires-Dist: matplotlib>=2.0.0
Requires-Dist: libsvmdata>=0.3
Requires-Dist: scikit-learn>=1.0
Requires-Dist: xarray
Requires-Dist: download
Requires-Dist: tqdm
Provides-Extra: doc
Requires-Dist: numpydoc; extra == "doc"
Requires-Dist: pandas; extra == "doc"
Requires-Dist: pillow; extra == "doc"
Requires-Dist: furo; extra == "doc"
Requires-Dist: sphinx-copybutton; extra == "doc"
Requires-Dist: sphinx-gallery; extra == "doc"
Dynamic: license-file
